fasttext_serving_protos/__init__.py
fasttext_serving_protos/model_pb2.py
fasttext_serving_protos/model_pb2_grpc.py
fasttext_serving_protos/service_pb2.py
fasttext_serving_protos/service_pb2_grpc.py
fasttext_serving_protos-0.0.13.dist-info/METADATA
fasttext_serving_protos-0.0.13.dist-info/WHEEL
fasttext_serving_protos-0.0.13.dist-info/top_level.txt
fasttext_serving_protos-0.0.13.dist-info/RECORD
