Metadata-Version: 2.1
Name: fasttext-serving-protos
Version: 0.0.13
Summary: FastText Serving Protocol Bufers Python implementation
Home-page: UNKNOWN
Author: NielsenIQ
Author-email: gonzalo.delafuente.consultant@nielseniq.com
License: UNKNOWN
Platform: UNKNOWN
Classifier: Programming Language :: Python :: 3
Classifier: License :: OSI Approved :: Apache Software License
Classifier: Operating System :: OS Independent
Requires-Python: >=3.0
